agealyser/__init__.py
agealyser/agealyser_enums.py
agealyser/main.py
agealyser/module.py
agealyser/utils.py
age_alyser-0.0.5.dist-info/METADATA
age_alyser-0.0.5.dist-info/WHEEL
age_alyser-0.0.5.dist-info/top_level.txt
age_alyser-0.0.5.dist-info/RECORD
