Metadata-Version: 2.2
Name: age-alyser
Version: 0.0.5
Summary: A python package for extracting key features of an AOE2 recorded games
Author-email: Benjamin Byrnes <b.byrnesy@gmail.com>
License: MIT
Project-URL: Homepage, https://github.com/byrnesy924/AgeAlyser_2
Project-URL: Issues, https://github.com/byrnesy924/AgeAlyser_2/issues
Keywords: statistics,AOE2,Age of Empires,parsing,mgz
Classifier: Programming Language :: Python :: 3
Classifier: Operating System :: OS Independent
Classifier: License :: OSI Approved :: MIT License
Requires-Python: >=3.11
Requires-Dist: mgz>=1.8.28
Requires-Dist: pandas>=2.2.2
Requires-Dist: numpy>=2.0.0
Requires-Dist: scipy>=1.14.0
Requires-Dist: shapely>=2.0.5
